{
  "files": {
    "incoming": {
      "fashion-dataset.zip": {
        "dirs": {
          "D1": "/fashion-dataset/fashion-dataset/images/",
          "D2": "/fashion-dataset/fashion-dataset/styles/"
        }
      },
      "archive.zip": {}
    },
    "outgoing": {
      "fashion-dataset_filestore.h5": {
        "groups": {
          "FG1": "/fashion-dataset/images/",
          "FG2": "/fashion-dataset/styles/",
          "FG3": "/fashion-dataset/video/"
        }
      },
    "leaf_content": {
      "images/": {
           "sources": [
            "jpg",
            "jpeg",
            "png",
            "bmp",
            "tiff",
            "blp",
            "bufr",
            "cur",
            "dcx",
            "dib",
            "eps",
            "fits",
            "gif",
            "jfif",
            "jpe",
            "ico",
            "icns",
            "j2c",
            "j2k",
            "jp2",
            "jpc",
            "jpx",
            "pcx",
            "pxr",
            "pgm",
            "ppm",
            "sgi",
            "svg",
            "csv"
          ]
    },
      "styles/": {
        "sources": ["json", "csv"]
        },
      "video/": {
         "sources": [
            "mpeg",
            "mp4",
            "mp3"
          ]
        }
      }
    }
   }
  }
